jax_quantity/__init__.py
jax_quantity/_base.py
jax_quantity/_core.py
jax_quantity/_fast.py
jax_quantity/_register_dispatches.py
jax_quantity/_register_primitives.py
jax_quantity/_version.py
jax_quantity/_version.pyi
jax_quantity/py.typed
jax_quantity-0.3.2.dist-info/METADATA
jax_quantity-0.3.2.dist-info/WHEEL
jax_quantity-0.3.2.dist-info/licenses/LICENSE
jax_quantity-0.3.2.dist-info/RECORD
