Metadata-Version: 2.1
Name: jax-quantity
Version: 0.3.2
Summary: Quantities in JAX
Project-URL: Bug Tracker, https://github.com/GalacticDynamics/jax-quantity/issues
Project-URL: Changelog, https://github.com/GalacticDynamics/jax-quantity/releases
Project-URL: Discussions, https://github.com/GalacticDynamics/jax-quantity/discussions
Project-URL: Homepage, https://github.com/GalacticDynamics/jax-quantity
Author-email: Nathaniel Starkman <nstarman@users.noreply.github.com>
License: BSD 3-Clause License
License-File: LICENSE
Classifier: Development Status :: 1 - Planning
Classifier: Intended Audience :: Developers
Classifier: Intended Audience :: Science/Research
Classifier: License :: OSI Approved :: BSD License
Classifier: Operating System :: OS Independent
Classifier: Programming Language :: Python
Classifier: Programming Language :: Python :: 3
Classifier: Programming Language :: Python :: 3 :: Only
Classifier: Programming Language :: Python :: 3.10
Classifier: Programming Language :: Python :: 3.11
Classifier: Programming Language :: Python :: 3.12
Classifier: Topic :: Scientific/Engineering
Classifier: Typing :: Typed
Requires-Python: >=3.10
Requires-Dist: astropy
Requires-Dist: equinox
Requires-Dist: jax
Requires-Dist: jaxlib
Requires-Dist: jaxtyping
Requires-Dist: quax>=0.0.3
Requires-Dist: quaxed>=0.3
Provides-Extra: all
Requires-Dist: jax-quantity[dev]; extra == 'all'
Requires-Dist: jax-quantity[docs]; extra == 'all'
Requires-Dist: jax-quantity[test]; extra == 'all'
Provides-Extra: dev
Requires-Dist: jax-quantity[test]; extra == 'dev'
Provides-Extra: docs
Requires-Dist: furo>=2023.08.17; extra == 'docs'
Requires-Dist: myst-parser>=0.13; extra == 'docs'
Requires-Dist: sphinx-autodoc-typehints; extra == 'docs'
Requires-Dist: sphinx-copybutton; extra == 'docs'
Requires-Dist: sphinx>=7.0; extra == 'docs'
Provides-Extra: test
Requires-Dist: hypothesis[numpy]; extra == 'test'
Requires-Dist: pytest-arraydiff; extra == 'test'
Requires-Dist: pytest-cov>=3; extra == 'test'
Requires-Dist: pytest<8,>=6; extra == 'test'
Requires-Dist: sybil; extra == 'test'
